tianmoucv2/__init__.py
tianmoucv2-0.0.0.1.dist-info/licenses/LICENSE
tianmoucv2-0.0.0.1.dist-info/METADATA
tianmoucv2-0.0.0.1.dist-info/WHEEL
tianmoucv2-0.0.0.1.dist-info/top_level.txt
tianmoucv2-0.0.0.1.dist-info/RECORD
