Metadata-Version: 2.4
Name: tianmoucv2
Version: 0.0.0.1
Summary: Algorithms library for Tianmouc sensor
Home-page: https://github.com/Tianmouc/tianmoucv
Author: Yihan Lin
Author-email: 532109881@qq.com
Keywords: tianmoucv2
Classifier: Programming Language :: Python :: 3 :: Only
Classifier: License :: OSI Approved :: MIT License
Classifier: Operating System :: OS Independent
Classifier: Intended Audience :: Developers
Requires-Python: >=3.8
License-File: LICENSE
Requires-Dist: charset-normalizer>=3.1.0
Requires-Dist: matplotlib>=3.2.2
Requires-Dist: numpy>=1.18.5
Requires-Dist: opencv-python>=4.1.1
Requires-Dist: scipy>=1.4.1
Requires-Dist: tqdm>=4.64.0
Requires-Dist: tensorboard>=2.4.1
Requires-Dist: pandas>=1.1.4
Requires-Dist: seaborn>=0.11.0
Requires-Dist: pybind11
Requires-Dist: requests
Requires-Dist: torch
Requires-Dist: torchvision
Requires-Dist: ipython
Requires-Dist: thop>=0.1.1
Dynamic: author
Dynamic: author-email
Dynamic: classifier
Dynamic: description
Dynamic: home-page
Dynamic: keywords
Dynamic: license-file
Dynamic: requires-dist
Dynamic: requires-python
Dynamic: summary
